pyroaring.cpython-38-arm-linux-gnueabihf.so
pyroaring/__init__.pyi
pyroaring/py.typed
pyroaring.libs/libgcc_s-85128ff4.so.1
pyroaring.libs/libstdc++-9ce46ac9.so.6.0.33
pyroaring-1.0.3.dist-info/LICENSE
pyroaring-1.0.3.dist-info/METADATA
pyroaring-1.0.3.dist-info/WHEEL
pyroaring-1.0.3.dist-info/top_level.txt
pyroaring-1.0.3.dist-info/RECORD
