Metadata-Version: 2.1
Name: pyroaring
Version: 1.0.3
Summary: Library for handling efficiently sorted integer sets.
Home-page: https://github.com/Ezibenroc/PyRoaringBitMap
Author: Tom Cornebize
Author-email: tom.cornebize@gmail.com
License: MIT
Classifier: License :: OSI Approved :: MIT License
Classifier: Intended Audience :: Developers
Classifier: Operating System :: POSIX :: Linux
Classifier: Operating System :: MacOS :: MacOS X
Classifier: Operating System :: Microsoft :: Windows
Classifier: Programming Language :: Python :: 3.8
Classifier: Programming Language :: Python :: 3.9
Classifier: Programming Language :: Python :: 3.10
Classifier: Programming Language :: Python :: 3.11
Classifier: Programming Language :: Python :: 3.12
Classifier: Programming Language :: Python :: 3.13
License-File: LICENSE
